ifmap/__init__.py
ifmap/__main__.py
ifmap/argument.py
ifmap/core.py
ifmap/plugins/__init__.py
ifmap/plugins/aws.py
ifmap/plugins/batch.py
ifmap/plugins/docker.py
ifmap/plugins/interface.py
tests/__init__.py
ifmap-1.0.22.dist-info/LICENSE
ifmap-1.0.22.dist-info/METADATA
ifmap-1.0.22.dist-info/WHEEL
ifmap-1.0.22.dist-info/top_level.txt
ifmap-1.0.22.dist-info/RECORD
