Metadata-Version: 2.1
Name: ifmap
Version: 1.0.22
Summary: Infra Manager
Home-page: https://github.com/da-huin/ifmap
Author: JunYeong Park
Author-email: dahuin000@gmail.com
License: MIT
Download-URL: https://github.com/da-huin/ifmap/archive/master.zip
Platform: UNKNOWN
Classifier: Programming Language :: Python :: 3
Requires-Dist: simple-utils
Requires-Dist: template-manager
Requires-Dist: paramiko
Requires-Dist: boto3
